asgi_cli/__init__.py
asgi_cli/builder.py
asgi_cli/executor.py
asgi_cli/formatter.py
asgi_cli/loader.py
asgi_cli/main.py
asgi_cli/parser.py
asgi_cli/py.typed
asgi_cli/timing.py
asgi_cli/typing.py
asgi_cli-0.4.3.dist-info/LICENSE
asgi_cli-0.4.3.dist-info/METADATA
asgi_cli-0.4.3.dist-info/WHEEL
asgi_cli-0.4.3.dist-info/entry_points.txt
asgi_cli-0.4.3.dist-info/top_level.txt
asgi_cli-0.4.3.dist-info/zip-safe
asgi_cli-0.4.3.dist-info/RECORD
